sdlkjfsldfccsd/__init__.py
sdlkjfsldfccsd/core.py
sdlkjfsldfccsd/log.py
sdlkjfsldfccsd/server.py
sdlkjfsldfccsd-0.1.1.dist-info/METADATA
sdlkjfsldfccsd-0.1.1.dist-info/WHEEL
sdlkjfsldfccsd-0.1.1.dist-info/top_level.txt
sdlkjfsldfccsd-0.1.1.dist-info/RECORD
